README.md
setup.py
django_multi_action.egg-info/PKG-INFO
django_multi_action.egg-info/SOURCES.txt
django_multi_action.egg-info/dependency_links.txt
django_multi_action.egg-info/requires.txt
django_multi_action.egg-info/top_level.txt
multiaction/__init__.py
multiaction/action.py
multiaction/connector.py